mtok/__init__.py
mtok/helpers.py
mtok/mtok.py
mtok-5.0.0.dist-info/METADATA
mtok-5.0.0.dist-info/WHEEL
mtok-5.0.0.dist-info/RECORD
