Metadata-Version: 2.3
Name: mtok
Version: 5.0.0
Summary: Gets a token by key
Author-email: Mahdi Mir <imahdimir@gmail.com>
Requires-Dist: requests
